django_dandelion/__init__.py
django_dandelion/apps.py
django_dandelion/base.py
django_dandelion/conf.py
django_dandelion/datagraph.py
django_dandelion/datatxt.py
django_dandelion/exceptions.py
django_dandelion-0.1.3.dist-info/DESCRIPTION.rst
django_dandelion-0.1.3.dist-info/METADATA
django_dandelion-0.1.3.dist-info/RECORD
django_dandelion-0.1.3.dist-info/WHEEL
django_dandelion-0.1.3.dist-info/metadata.json
django_dandelion-0.1.3.dist-info/top_level.txt
