Metadata-Version: 2.0
Name: django-dandelion
Version: 0.1.3
Summary: Use the Dandelion API with Django
Home-page: https://github.com/AlessioBazzanella/django-dandelion
Author: Alessio Bazzanella
Author-email: alessio.bazzanella@me.com
License: MIT
Keywords: django-dandelion,dandelion,api,semantic text analytics
Platform: UNKNOWN
Classifier: Development Status :: 3 - Alpha
Classifier: Framework :: Django
Classifier: Framework :: Django :: 1.8
Classifier: Framework :: Django :: 1.9
Classifier: Framework :: Django :: 1.10
Classifier: Intended Audience :: Developers
Classifier: License :: OSI Approved :: BSD License
Classifier: Natural Language :: English
Classifier: Programming Language :: Python :: 2
Classifier: Programming Language :: Python :: 2.7
Classifier: Programming Language :: Python :: 3
Classifier: Programming Language :: Python :: 3.3
Classifier: Programming Language :: Python :: 3.4
Classifier: Programming Language :: Python :: 3.5
Requires-Dist: Django (>=1.8)
Requires-Dist: requests (>=2.13.0)
Requires-Dist: six (>=1.10.0)
